Workbook

Sheet Pivote (2)
A2: VP | B2: (Todas)
A3: Classif | B3: Expenses
A5: Etiquetas de fila | B5: Suma de YTD | C5: Suma de Forecast FY | D5: Suma de Budget FY | E5: Suma de BYTD | F5: Suma de Forecast Actual
A6: Gerencia Técnica y Desarrollo | B6: 71262.193 | C6: 213786.58 | D6: 286993.45 | E6: 104095.6 | F6: 20171.12
A7: Gerente Análisis y Desarrollo de Negocios | B7: 10949.485 | C7: 32848.456 | D7: 32580 | E7: 26210 | F7: 22570
A8: Gerente Asuntos Corporativos | B8: 661720.91 | C8: 1985162.7 | D8: 2784876 | E8: 1274035 | F8: 195231
A9: Gerente Chancado y Correas | B9: 56556.984 | C9: 169670.95 | D9: 228670.34 | E9: 90216.807 | F9: 19343.361
A10: Gerente Contralor | B10: 236564.28 | C10: 709692.85 | D10: 1500369.6 | E10: 613097.22 | F10: 76268.218
A11: Gerente Contratos | B11: 28133.206 | C11: 84399.617 | D11: 134072.97 | E11: 55863.737 | F11: 11172.747
A12: Gerente Control Gestión y Reportes | B12: 21889.334 | C12: 65668.001 | D12: 88665.33 | E12: 36945.554 | F12: 9567.1108
A13: Gerente de Abastecimiento | B13: 722749.44 | C13: 2168248.3 | D13: 2799332.7 | E13: 1166388.6 | F13: 233277.72
A14: Gerente de Puerto | B14: 269901.29 | C14: 809703.88 | D14: 1139202.7 | E14: 469169.2 | F14: 92813.89
A15: Gerente Desarrollo Lixiviación | B15: 32127.122 | C15: 96381.366 | D15: 195705.17 | E15: 71502.153 | F15: 13600.431
A16: Gerente Desarrollo Personas y Organización | B16: 1965139.1 | C16: 5895417.4 | D16: 9889533.7 | E16: 3386107.6 | F16: 807463.25
A17: Gerente Embarques y Logísticas | B17: 16266.378 | C17: 48799.133 | D17: 110781 | E17: 40172.333 | F17: 5070.6667
... A100: Total general | B100: 68943398 | C100: 2.0683019e+08 | D100: 2.8883223e+08 | E100: 1.1850057e+08 | F100: 24005235

Sheet GRUPOS
A1: RESPONSABILIDAD | B1: CLASS | C1: GRUPOS
A2: VP - RRHH | B2: RH | C2: 5 - 10
A3: VP - Operaciones Planta | B3: OP | C3: 13
A4: VP - Operaciones Mina | B4: OM | C4: 13
A5: VP - Legal, Asuntos, Corporativos y Comunidad | B5: SG | C5: 6 - 11
A6: VP - Gestión de Activos | B6: SO | C6: 7 - 12
A7: VP - Finanzas y Ventas | B7: AS | C7: 1 - 6
A8: VP - Desarrollo | B8: PR | C8: 4 - 9
A9: VP - Administración y Servicios | B9: AS | C9: 1 - 6
A10: Ste. Telecomunicaciones y Redes | B10: AS | C10: 1 - 6
A11: Ste. Suministro y Calidad Aguas | B11: SO | C11: 7 - 12
A12: Ste. Servicios Mina | B12: OM | C12: 2 - 7
... A99: Gerencia Técnica y Desarrollo | B99: SG | C99: 6 - 11

Sheet Budget
A1: Resp | B1: Desc Resp | C1: VP | D1: Gerencia | E1: Proc | F1: Desc Proc | G1: Item | H1: Desc Item | I1: Classif | J1: CC | K1: Jan-25 | L1: Feb-25 | M1: Mar-25 | N1: Apr-25 | O1: May-25 | P1: Jun-25 | Q1: Jul-25 | R1: Aug-25 | S1: Sep-25 | T1: Oct-25 | U1: Nov-25 | V1: Dec-25 | W1: FY25 | X1: FY26 | Y1: FY27 | Z1: FY28 | AA1: FY29 | AB1: BYTD
A2: 1000 | B2: Presidencia Ejecutiva | C2: CEO | D2: CEO | E2: 1001 | F2: Dpto. Direccion Compañia | G2: 3101 | H2: Remuneraciones Supervision | I2: Labor | J2: 100010013101 | K2: 37029.29 | L2: 32159.15 | M2: 32159.15 | N2: 39824.64 | O2: 33365.77 | P2: 35176.19 | Q2: 38235.92 | R2: 33365.77 | S2: 33365.77 | T2: 38663.36 | U2: 33793.22 | V2: 38858.81 | W2: 425997.04 | X2: 434632.82 | Y2: 451782.75 | Z2: 464582.25 | AA2: 489506.59 | AB2: =SUM(K2:O2) -> 174538
A3: 1000 | B3: Presidencia Ejecutiva | C3: CEO | D3: CEO | E3: 1001 | F3: Dpto. Direccion Compañia | G3: 5111 | H3: Pasajes Nacionales | I3: Expenses | J3: 100010015111 | K3: 3000 | L3: 3000 | M3: 3000 | N3: 3000 | O3: 3000 | P3: 3000 | Q3: 3000 | R3: 3000 | S3: 3000 | T3: 3000 | U3: 3000 | V3: 3000 | W3: 36000 | X3: 36034.929 | Y3: 36123.346 | Z3: 36604.546 | AA3: 36877.525 | AB3: =SUM(K3:O3) -> 15000
A4: 1000 | B4: Presidencia Ejecutiva | C4: CEO | D4: CEO | E4: 1001 | F4: Dpto. Direccion Compañia | G4: 5112 | H4: Hoteles Estadia Alimentacion Nacionales | I4: Expenses | J4: 100010015112 | K4: 800 | L4: 800 | M4: 800 | N4: 800 | O4: 800 | P4: 800 | Q4: 800 | R4: 800 | S4: 800 | T4: 800 | U4: 800 | V4: 800 | W4: 9600 | X4: 9609.3143 | Y4: 9632.8922 | Z4: 9761.2123 | AA4: 9834.0066 | AB4: =SUM(K4:O4) -> 4000
A5: 1000 | B5: Presidencia Ejecutiva | C5: CEO | D5: CEO | E5: 1001 | F5: Dpto. Direccion Compañia | G5: 5113 | H5: Gastos Representacion Nacionales | I5: Expenses | J5: 100010015113 | K5: 350 | L5: 350 | M5: 350 | N5: 350 | O5: 350 | P5: 350 | Q5: 350 | R5: 350 | S5: 350 | T5: 350 | U5: 350 | V5: 350 | W5: 4200 | X5: 4220.9928 | Y5: 4307.6666 | Z5: 4416.6049 | AA5: 4466.8551 | AB5: =SUM(K5:O5) -> 1750
A6: 1000 | B6: Presidencia Ejecutiva | C6: CEO | D6: CEO | E6: 1001 | F6: Dpto. Direccion Compañia | G6: 5121 | H6: Pasajes Internacionales | I6: Expenses | J6: 100010015121 | K6: 0 | L6: 0 | M6: 8050 | N6: 0 | O6: 0 | P6: 0 | Q6: 0 | R6: 0 | S6: 8050 | T6: 8050 | U6: 0 | V6: 0 | W6: 24150 | X6: 24415.65 | Y6: 24757.469 | Z6: 25128.831 | AA6: 25505.764 | AB6: =SUM(K6:O6) -> 8050
A7: 1000 | B7: Presidencia Ejecutiva | C7: CEO | D7: CEO | E7: 1001 | F7: Dpto. Direccion Compañia | G7: 5122 | H7: Hoteles Estadia Alimentacion Extranjero | I7: Expenses | J7: 100010015122 | K7: 0 | L7: 0 | M7: 2500 | N7: 0 | O7: 0 | P7: 0 | Q7: 0 | R7: 0 | S7: 2500 | T7: 2500 | U7: 0 | V7: 0 | W7: 7500 | X7: 7582.5 | Y7: 7688.655 | Z7: 7803.9848 | AA7: 7921.0446 | AB7: =SUM(K7:O7) -> 2500
A8: 1000 | B8: Presidencia Ejecutiva | C8: CEO | D8: CEO | E8: 1001 | F8: Dpto. Direccion Compañia | G8: 5123 | H8: Gastos Representacion Extranjero | I8: Expenses | J8: 100010015123 | K8: 0 | L8: 0 | M8: 1500 | N8: 0 | O8: 0 | P8: 0 | Q8: 0 | R8: 0 | S8: 1500 | T8: 1500 | U8: 0 | V8: 0 | W8: 4500 | X8: 4549.5 | Y8: 4613.193 | Z8: 4682.3909 | AA8: 4752.6268 | AB8: =SUM(K8:O8) -> 1500
A9: 1000 | B9: Presidencia Ejecutiva | C9: CEO | D9: CEO | E9: 1001 | F9: Dpto. Direccion Compañia | G9: 5201 | H9: Arriendo Vehiculos | I9: Expenses | J9: 100010015201 | K9: 1431.4538 | L9: 1431.4538 | M9: 1431.4538 | N9: 1431.4538 | O9: 1431.4538 | P9: 1431.4538 | Q9: 1431.4538 | R9: 1431.4538 | S9: 1431.4538 | T9: 1431.4538 | U9: 1431.4538 | V9: 1431.4538 | W9: 17177.446 | X9: 17263.303 | Y9: 17617.788 | Z9: 18063.331 | AA9: 18268.848 | AB9: =SUM(K9:O9) -> 7157.269
A10: 1000 | B10: Presidencia Ejecutiva | C10: CEO | D10: CEO | E10: 1001 | F10: Dpto. Direccion Compañia | G10: 5203 | H10: Combustibles | I10: Expenses | J10: 100010015203 | K10: 300 | L10: 300 | M10: 300 | N10: 300 | O10: 300 | P10: 300 | Q10: 300 | R10: 300 | S10: 300 | T10: 300 | U10: 300 | V10: 300 | W10: 3600 | X10: 3632.4948 | Y10: 3724.2661 | Z10: 3821.0138 | AA10: 3876.2211 | AB10: =SUM(K10:O10) -> 1500
A11: 1000 | B11: Presidencia Ejecutiva | C11: CEO | D11: CEO | E11: 1001 | F11: Dpto. Direccion Compañia | G11: 5301 | H11: Materiales y Utiles de Escritorio | I11: Expenses | J11: 100010015301 | K11: 350 | L11: 0 | M11: 0 | N11: 350 | O11: 0 | P11: 0 | Q11: 350 | R11: 0 | S11: 0 | T11: 350 | U11: 0 | V11: 0 | W11: 1400 | X11: 1406.9976 | Y11: 1435.8889 | Z11: 1472.2016 | AA11: 1488.9517 | AB11: =SUM(K11:O11) -> 700
A12: 1000 | B12: Presidencia Ejecutiva | C12: CEO | D12: CEO | E12: 1001 | F12: Dpto. Direccion Compañia | G12: 5302 | H12: Suscripciones Varias (Fisicas y Electron | I12: Expenses | J12: 100010015302 | K12: 833.33333 | L12: 833.33333 | M12: 833.33333 | N12: 833.33333 | O12: 833.33333 | P12: 833.33333 | Q12: 833.33333 | R12: 833.33333 | S12: 833.33333 | T12: 833.33333 | U12: 833.33333 | V12: 833.33333 | W12: 10000 | X12: 10049.983 | Y12: 10256.349 | Z12: 10515.726 | AA12: 10635.369 | AB12: =SUM(K12:O12) -> 4166.6667
A13: 1000 | B13: Presidencia Ejecutiva | C13: CEO | D13: CEO | E13: 1001 | F13: Dpto. Direccion Compañia | G13: 5411 | H13: Ropa y Equipos Proteccion Personal | I13: Expenses | J13: 100010015411 | K13: 110 | L13: 110 | M13: 110 | N13: 110 | O13: 110 | P13: 110 | Q13: 110 | R13: 110 | S13: 110 | T13: 110 | U13: 110 | V13: 110 | W13: 1320 | X13: 1321.2807 | Y13: 1324.5227 | Z13: 1342.1667 | AA13: 225.36265 | AB13: =SUM(K13:O13) -> 550
... A2575: 2861 | B2575: Ste. Accionamiento de Maquinas Eléctricas e Ingeniería | C2575: VPO PLANTAS | D2575: Gerencia Mantención Concentradora | E2575: 5751 | F2575: Dpto. Mantencion Plantas | G2575: 6148 | H2575: Gastos Cafeteria | I2575: Expenses | J2575: 286157516148 | K2575: 500 | L2575: 500 | M2575: 500 | N2575: 500 | O2575: 500 | P2575: 500 | Q2575: 500 | R2575: 500 | S2575: 500 | T2575: 500 | U2575: 500 | V2575: 500 | W2575: 6000 | X2575: 6005.8214 | Y2575: 6020.5576 | Z2575: 6100.7577 | AA2575: 6146.2542 | AB2575: =SUM(K2575:O2575) -> 2500
AB2576: =SUM(K2576:O2576) -> 0
AB2577: =SUM(K2577:O2577) -> 0
AB2578: =SUM(K2578:O2578) -> 0
AB2579: =SUM(K2579:O2579) -> 0
AB2580: =SUM(K2580:O2580) -> 0
AB2581: =SUM(K2581:O2581) -> 0
AB2582: =SUM(K2582:O2582) -> 0
AB2583: =SUM(K2583:O2583) -> 0
AB2584: =SUM(K2584:O2584) -> 0
AB2585: =SUM(K2585:O2585) -> 0
AB2586: =SUM(K2586:O2586) -> 0

Sheet Gastos
A1: Resp | B1: Desc Resp | C1: VP | D1: Gerencia | E1: Proc | F1: Desc Proc | G1: Item | H1: Desc Item | I1: Classif | J1: CC | K1: Jan-25 | L1: Feb-25 | M1: Mar-25 | N1: Apr-25 | O1: May-25 | P1: Jun-25 | Q1: Jul-25 | R1: Aug-25 | S1: Sep-25 | T1: Oct-25 | U1: Nov-25 | V1: Dec-25 | W1: YTD | X1: Forecast FY | Y1: Budget FY | Z1: Var | AA1: BYTD | AB1: Forecast Actual
A2: 1000 | B2: Presidencia Ejecutiva | C2: CEO | D2: CEO | E2: 1001 | F2: Dpto. Direccion Compañia | G2: 3101 | H2: Remuneraciones Supervision | I2: Labor | J2: 100010013101 | K2: 37029.29 | L2: 32159.15 | M2: 32159.15 | N2: 39824.64 | O2: 38231.654 | P2: =SUM($K2:$O2)/5 -> 35880.777 | Q2: =SUM($K2:$O2)/5 -> 35880.777 | R2: =SUM($K2:$O2)/5 -> 35880.777 | S2: =SUM($K2:$O2)/5 -> 35880.777 | T2: =SUM($K2:$O2)/5 -> 35880.777 | U2: =SUM($K2:$O2)/5 -> 35880.777 | V2: =SUM($K2:$O2)/5 -> 35880.777 | W2: =SUM(K2:O2) -> 179403.88 | X2: =SUM(K2:V2) -> 430569.32 | Y2: =VLOOKUP(J2,[1]BD!$J$2:$W$2575,14,FALSE) -> 425997.04 | Z2: =Y2-X2 -> -4572.2826 | AA2: =VLOOKUP(J2,Budget!$J$2:$AB$2575,19,FALSE) -> 174538 | AB2: =VLOOKUP(J2,Budget!$J$2:$AB$2575,5,FALSE) -> 39824.64
A3: 1000 | B3: Presidencia Ejecutiva | C3: CEO | D3: CEO | E3: 1001 | F3: Dpto. Direccion Compañia | G3: 5111 | H3: Pasajes Nacionales | I3: Expenses | J3: 100010015111 | K3: 2424.0128 | L3: 3464.9197 | M3: 1635.9109 | N3: 1559.6104 | O3: 1497.2259 | P3: =SUM($K3:$O3)/5 -> 2116.3359 | Q3: =SUM($K3:$O3)/5 -> 2116.3359 | R3: =SUM($K3:$O3)/5 -> 2116.3359 | S3: =SUM($K3:$O3)/5 -> 2116.3359 | T3: =SUM($K3:$O3)/5 -> 2116.3359 | U3: =SUM($K3:$O3)/5 -> 2116.3359 | V3: =SUM($K3:$O3)/5 -> 2116.3359 | W3: =SUM(K3:O3) -> 10581.68 | X3: =SUM(K3:V3) -> 25396.031 | Y3: =VLOOKUP(J3,[1]BD!$J$2:$W$2575,14,FALSE) -> 36000 | Z3: =Y3-X3 -> 10603.969 | AA3: =VLOOKUP(J3,Budget!$J$2:$AB$2575,19,FALSE) -> 15000 | AB3: =VLOOKUP(J3,Budget!$J$2:$AB$2575,5,FALSE) -> 3000
A4: 1000 | B4: Presidencia Ejecutiva | C4: CEO | D4: CEO | E4: 1001 | F4: Dpto. Direccion Compañia | G4: 5112 | H4: Hoteles Estadia Alimentacion Nacionales | I4: Expenses | J4: 100010015112 | K4: 96.282754 | L4: 354.97862 | M4: 787.2742 | N4: 1065.9745 | O4: 1023.3355 | P4: =SUM($K4:$O4)/5 -> 665.56911 | Q4: =SUM($K4:$O4)/5 -> 665.56911 | R4: =SUM($K4:$O4)/5 -> 665.56911 | S4: =SUM($K4:$O4)/5 -> 665.56911 | T4: =SUM($K4:$O4)/5 -> 665.56911 | U4: =SUM($K4:$O4)/5 -> 665.56911 | V4: =SUM($K4:$O4)/5 -> 665.56911 | W4: =SUM(K4:O4) -> 3327.8456 | X4: =SUM(K4:V4) -> 7986.8294 | Y4: =VLOOKUP(J4,[1]BD!$J$2:$W$2575,14,FALSE) -> 9600 | Z4: =Y4-X4 -> 1613.1706 | AA4: =VLOOKUP(J4,Budget!$J$2:$AB$2575,19,FALSE) -> 4000 | AB4: =VLOOKUP(J4,Budget!$J$2:$AB$2575,5,FALSE) -> 800
A5: 1000 | B5: Presidencia Ejecutiva | C5: CEO | D5: CEO | E5: 1001 | F5: Dpto. Direccion Compañia | G5: 5113 | H5: Gastos Representacion Nacionales | I5: Expenses | J5: 100010015113 | K5: 444.35266 | L5: 455.23367 | M5: 222.76814 | N5: 389.52186 | O5: 373.94098 | P5: =SUM($K5:$O5)/5 -> 377.16346 | Q5: =SUM($K5:$O5)/5 -> 377.16346 | R5: =SUM($K5:$O5)/5 -> 377.16346 | S5: =SUM($K5:$O5)/5 -> 377.16346 | T5: =SUM($K5:$O5)/5 -> 377.16346 | U5: =SUM($K5:$O5)/5 -> 377.16346 | V5: =SUM($K5:$O5)/5 -> 377.16346 | W5: =SUM(K5:O5) -> 1885.8173 | X5: =SUM(K5:V5) -> 4525.9616 | Y5: =VLOOKUP(J5,[1]BD!$J$2:$W$2575,14,FALSE) -> 4200 | Z5: =Y5-X5 -> -325.96156 | AA5: =VLOOKUP(J5,Budget!$J$2:$AB$2575,19,FALSE) -> 1750 | AB5: =VLOOKUP(J5,Budget!$J$2:$AB$2575,5,FALSE) -> 350
A6: 1000 | B6: Presidencia Ejecutiva | C6: CEO | D6: CEO | E6: 1001 | F6: Dpto. Direccion Compañia | G6: 5121 | H6: Pasajes Internacionales | I6: Expenses | J6: 100010015121 | K6: 0 | L6: 0 | M6: 5943.2671 | N6: 0 | P6: =SUM($K6:$O6)/5 -> 1188.6534 | Q6: =SUM($K6:$O6)/5 -> 1188.6534 | R6: =SUM($K6:$O6)/5 -> 1188.6534 | S6: =SUM($K6:$O6)/5 -> 1188.6534 | T6: =SUM($K6:$O6)/5 -> 1188.6534 | U6: =SUM($K6:$O6)/5 -> 1188.6534 | V6: =SUM($K6:$O6)/5 -> 1188.6534 | W6: =SUM(K6:O6) -> 5943.2671 | X6: =SUM(K6:V6) -> 14263.841 | Y6: =VLOOKUP(J6,[1]BD!$J$2:$W$2575,14,FALSE) -> 24150 | Z6: =Y6-X6 -> 9886.1589 | AA6: =VLOOKUP(J6,Budget!$J$2:$AB$2575,19,FALSE) -> 8050 | AB6: =VLOOKUP(J6,Budget!$J$2:$AB$2575,5,FALSE) -> 0
A7: 1000 | B7: Presidencia Ejecutiva | C7: CEO | D7: CEO | E7: 1001 | F7: Dpto. Direccion Compañia | G7: 5122 | H7: Hoteles Estadia Alimentacion Extranjero | I7: Expenses | J7: 100010015122 | K7: 0 | L7: 0 | M7: 1345.7872 | N7: 0 | O7: 336.44681 | P7: =SUM($K7:$O7)/5 -> 336.44681 | Q7: =SUM($K7:$O7)/5 -> 336.44681 | R7: =SUM($K7:$O7)/5 -> 336.44681 | S7: =SUM($K7:$O7)/5 -> 336.44681 | T7: =SUM($K7:$O7)/5 -> 336.44681 | U7: =SUM($K7:$O7)/5 -> 336.44681 | V7: =SUM($K7:$O7)/5 -> 336.44681 | W7: =SUM(K7:O7) -> 1682.234 | X7: =SUM(K7:V7) -> 4037.3617 | Y7: =VLOOKUP(J7,[1]BD!$J$2:$W$2575,14,FALSE) -> 7500 | Z7: =Y7-X7 -> 3462.6383 | AA7: =VLOOKUP(J7,Budget!$J$2:$AB$2575,19,FALSE) -> 2500 | AB7: =VLOOKUP(J7,Budget!$J$2:$AB$2575,5,FALSE) -> 0
A8: 1000 | B8: Presidencia Ejecutiva | C8: CEO | D8: CEO | E8: 1001 | F8: Dpto. Direccion Compañia | G8: 5123 | H8: Gastos Representacion Extranjero | I8: Expenses | J8: 100010015123 | K8: 0 | L8: 0 | M8: 2730.3759 | N8: 0 | O8: 682.59398 | P8: =SUM($K8:$O8)/5 -> 682.59398 | Q8: =SUM($K8:$O8)/5 -> 682.59398 | R8: =SUM($K8:$O8)/5 -> 682.59398 | S8: =SUM($K8:$O8)/5 -> 682.59398 | T8: =SUM($K8:$O8)/5 -> 682.59398 | U8: =SUM($K8:$O8)/5 -> 682.59398 | V8: =SUM($K8:$O8)/5 -> 682.59398 | W8: =SUM(K8:O8) -> 3412.9699 | X8: =SUM(K8:V8) -> 8191.1278 | Y8: =VLOOKUP(J8,[1]BD!$J$2:$W$2575,14,FALSE) -> 4500 | Z8: =Y8-X8 -> -3691.1278 | AA8: =VLOOKUP(J8,Budget!$J$2:$AB$2575,19,FALSE) -> 1500 | AB8: =VLOOKUP(J8,Budget!$J$2:$AB$2575,5,FALSE) -> 0
A9: 1000 | B9: Presidencia Ejecutiva | C9: CEO | D9: CEO | E9: 1001 | F9: Dpto. Direccion Compañia | G9: 5201 | H9: Arriendo Vehiculos | I9: Expenses | J9: 100010015201 | K9: 2544.0088 | L9: 393.08205 | M9: 777.27181 | N9: 1524.7633 | O9: 1309.7815 | P9: =SUM($K9:$O9)/5 -> 1309.7815 | Q9: =SUM($K9:$O9)/5 -> 1309.7815 | R9: =SUM($K9:$O9)/5 -> 1309.7815 | S9: =SUM($K9:$O9)/5 -> 1309.7815 | T9: =SUM($K9:$O9)/5 -> 1309.7815 | U9: =SUM($K9:$O9)/5 -> 1309.7815 | V9: =SUM($K9:$O9)/5 -> 1309.7815 | W9: =SUM(K9:O9) -> 6548.9075 | X9: =SUM(K9:V9) -> 15717.378 | Y9: =VLOOKUP(J9,[1]BD!$J$2:$W$2575,14,FALSE) -> 17177.446 | Z9: =Y9-X9 -> 1460.0677 | AA9: =VLOOKUP(J9,Budget!$J$2:$AB$2575,19,FALSE) -> 7157.269 | AB9: =VLOOKUP(J9,Budget!$J$2:$AB$2575,5,FALSE) -> 1431.4538
A10: 1000 | B10: Presidencia Ejecutiva | C10: CEO | D10: CEO | E10: 1001 | F10: Dpto. Direccion Compañia | G10: 5203 | H10: Combustibles | I10: Expenses | J10: 100010015203 | K10: 383.09717 | L10: 187.39678 | M10: 84.870051 | N10: 39.877977 | O10: 173.81049 | P10: =SUM($K10:$O10)/5 -> 173.81049 | Q10: =SUM($K10:$O10)/5 -> 173.81049 | R10: =SUM($K10:$O10)/5 -> 173.81049 | S10: =SUM($K10:$O10)/5 -> 173.81049 | T10: =SUM($K10:$O10)/5 -> 173.81049 | U10: =SUM($K10:$O10)/5 -> 173.81049 | V10: =SUM($K10:$O10)/5 -> 173.81049 | W10: =SUM(K10:O10) -> 869.05247 | X10: =SUM(K10:V10) -> 2085.7259 | Y10: =VLOOKUP(J10,[1]BD!$J$2:$W$2575,14,FALSE) -> 3600 | Z10: =Y10-X10 -> 1514.2741 | AA10: =VLOOKUP(J10,Budget!$J$2:$AB$2575,19,FALSE) -> 1500 | AB10: =VLOOKUP(J10,Budget!$J$2:$AB$2575,5,FALSE) -> 300
A11: 1000 | B11: Presidencia Ejecutiva | C11: CEO | D11: CEO | E11: 1001 | F11: Dpto. Direccion Compañia | G11: 5301 | H11: Materiales y Utiles de Escritorio | I11: Expenses | J11: 100010015301 | K11: 91.889409 | L11: 0 | M11: 0 | N11: 27.790561 | O11: 29.919993 | P11: =SUM($K11:$O11)/5 -> 29.919993 | Q11: =SUM($K11:$O11)/5 -> 29.919993 | R11: =SUM($K11:$O11)/5 -> 29.919993 | S11: =SUM($K11:$O11)/5 -> 29.919993 | T11: =SUM($K11:$O11)/5 -> 29.919993 | U11: =SUM($K11:$O11)/5 -> 29.919993 | V11: =SUM($K11:$O11)/5 -> 29.919993 | W11: =SUM(K11:O11) -> 149.59996 | X11: =SUM(K11:V11) -> 359.03991 | Y11: =VLOOKUP(J11,[1]BD!$J$2:$W$2575,14,FALSE) -> 1400 | Z11: =Y11-X11 -> 1040.9601 | AA11: =VLOOKUP(J11,Budget!$J$2:$AB$2575,19,FALSE) -> 700 | AB11: =VLOOKUP(J11,Budget!$J$2:$AB$2575,5,FALSE) -> 350
A12: 1000 | B12: Presidencia Ejecutiva | C12: CEO | D12: CEO | E12: 1001 | F12: Dpto. Direccion Compañia | G12: 5302 | H12: Suscripciones Varias (Fisicas y Electron | I12: Expenses | J12: 100010015302 | K12: 793.21168 | L12: 461.84635 | M12: 1003.2608 | N12: 558.29691 | O12: 704.15394 | P12: =SUM($K12:$O12)/5 -> 704.15394 | Q12: =SUM($K12:$O12)/5 -> 704.15394 | R12: =SUM($K12:$O12)/5 -> 704.15394 | S12: =SUM($K12:$O12)/5 -> 704.15394 | T12: =SUM($K12:$O12)/5 -> 704.15394 | U12: =SUM($K12:$O12)/5 -> 704.15394 | V12: =SUM($K12:$O12)/5 -> 704.15394 | W12: =SUM(K12:O12) -> 3520.7697 | X12: =SUM(K12:V12) -> 8449.8473 | Y12: =VLOOKUP(J12,[1]BD!$J$2:$W$2575,14,FALSE) -> 10000 | Z12: =Y12-X12 -> 1550.1527 | AA12: =VLOOKUP(J12,Budget!$J$2:$AB$2575,19,FALSE) -> 4166.6667 | AB12: =VLOOKUP(J12,Budget!$J$2:$AB$2575,5,FALSE) -> 833.33333
A13: 1000 | B13: Presidencia Ejecutiva | C13: CEO | D13: CEO | E13: 1001 | F13: Dpto. Direccion Compañia | G13: 5411 | H13: Ropa y Equipos Proteccion Personal | I13: Expenses | J13: 100010015411 | K13: 16.842278 | L13: 103.91089 | M13: 89.365215 | N13: 117.65956 | O13: 81.944486 | P13: =SUM($K13:$O13)/5 -> 81.944486 | Q13: =SUM($K13:$O13)/5 -> 81.944486 | R13: =SUM($K13:$O13)/5 -> 81.944486 | S13: =SUM($K13:$O13)/5 -> 81.944486 | T13: =SUM($K13:$O13)/5 -> 81.944486 | U13: =SUM($K13:$O13)/5 -> 81.944486 | V13: =SUM($K13:$O13)/5 -> 81.944486 | W13: =SUM(K13:O13) -> 409.72243 | X13: =SUM(K13:V13) -> 983.33383 | Y13: =VLOOKUP(J13,[1]BD!$J$2:$W$2575,14,FALSE) -> 1320 | Z13: =Y13-X13 -> 336.66617 | AA13: =VLOOKUP(J13,Budget!$J$2:$AB$2575,19,FALSE) -> 550 | AB13: =VLOOKUP(J13,Budget!$J$2:$AB$2575,5,FALSE) -> 110
A14: 1000 | B14: Presidencia Ejecutiva | C14: CEO | D14: CEO | E14: 1001 | F14: Dpto. Direccion Compañia | G14: 5501 | H14: Honorarios Consultores Nacionales | I14: Expenses | J14: 100010015501 | K14: 23104.262 | L14: 14086.806 | M14: 21125.583 | N14: 3307.3728 | O14: 15406.006 | P14: =SUM($K14:$O14)/5 -> 15406.006 | Q14: =SUM($K14:$O14)/5 -> 15406.006 | R14: =SUM($K14:$O14)/5 -> 15406.006 | S14: =SUM($K14:$O14)/5 -> 15406.006 | T14: =SUM($K14:$O14)/5 -> 15406.006 | U14: =SUM($K14:$O14)/5 -> 15406.006 | V14: =SUM($K14:$O14)/5 -> 15406.006 | W14: =SUM(K14:O14) -> 77030.031 | X14: =SUM(K14:V14) -> 184872.07 | Y14: =VLOOKUP(J14,[1]BD!$J$2:$W$2575,14,FALSE) -> 200000 | Z14: =Y14-X14 -> 15127.927 | AA14: =VLOOKUP(J14,Budget!$J$2:$AB$2575,19,FALSE) -> 83333.333 | AB14: =VLOOKUP(J14,Budget!$J$2:$AB$2575,5,FALSE) -> 16666.667
A15: 1000 | B15: Presidencia Ejecutiva | C15: CEO | D15: CEO | E15: 1001 | F15: Dpto. Direccion Compañia | G15: 5502 | H15: Honorarios Consultores Extranjeros | I15: Expenses | J15: 100010015502 | K15: 9762.8315 | L15: 4337.3148 | M15: 8789.6082 | N15: 14236.716 | O15: 9281.6177 | P15: =SUM($K15:$O15)/5 -> 9281.6177 | Q15: =SUM($K15:$O15)/5 -> 9281.6177 | R15: =SUM($K15:$O15)/5 -> 9281.6177 | S15: =SUM($K15:$O15)/5 -> 9281.6177 | T15: =SUM($K15:$O15)/5 -> 9281.6177 | U15: =SUM($K15:$O15)/5 -> 9281.6177 | V15: =SUM($K15:$O15)/5 -> 9281.6177 | W15: =SUM(K15:O15) -> 46408.088 | X15: =SUM(K15:V15) -> 111379.41 | Y15: =VLOOKUP(J15,[1]BD!$J$2:$W$2575,14,FALSE) -> 100000 | Z15: =Y15-X15 -> -11379.412 | AA15: =VLOOKUP(J15,Budget!$J$2:$AB$2575,19,FALSE) -> 41666.667 | AB15: =VLOOKUP(J15,Budget!$J$2:$AB$2575,5,FALSE) -> 8333.3333
A16: 1000 | B16: Presidencia Ejecutiva | C16: CEO | D16: CEO | E16: 1001 | F16: Dpto. Direccion Compañia | G16: 5503 | H16: Otros Gastos Consultores | I16: Expenses | J16: 100010015503 | K16: 3578.9645 | L16: 2134.3666 | M16: 789.00661 | N16: 2833.7561 | O16: 2334.0234 | P16: =SUM($K16:$O16)/5 -> 2334.0234 | Q16: =SUM($K16:$O16)/5 -> 2334.0234 | R16: =SUM($K16:$O16)/5 -> 2334.0234 | S16: =SUM($K16:$O16)/5 -> 2334.0234 | T16: =SUM($K16:$O16)/5 -> 2334.0234 | U16: =SUM($K16:$O16)/5 -> 2334.0234 | V16: =SUM($K16:$O16)/5 -> 2334.0234 | W16: =SUM(K16:O16) -> 11670.117 | X16: =SUM(K16:V16) -> 28008.281 | Y16: =VLOOKUP(J16,[1]BD!$J$2:$W$2575,14,FALSE) -> 48000 | Z16: =Y16-X16 -> 19991.719 | AA16: =VLOOKUP(J16,Budget!$J$2:$AB$2575,19,FALSE) -> 20000 | AB16: =VLOOKUP(J16,Budget!$J$2:$AB$2575,5,FALSE) -> 4000
A17: 1000 | B17: Presidencia Ejecutiva | C17: CEO | D17: CEO | E17: 1001 | F17: Dpto. Direccion Compañia | G17: 5603 | H17: Otros Gastos Reuniones | I17: Expenses | J17: 100010015603 | K17: 289.28992 | L17: 158.49001 | M17: 15.61342 | N17: 106.83602 | O17: 142.55734 | P17: =SUM($K17:$O17)/5 -> 142.55734 | Q17: =SUM($K17:$O17)/5 -> 142.55734 | R17: =SUM($K17:$O17)/5 -> 142.55734 | S17: =SUM($K17:$O17)/5 -> 142.55734 | T17: =SUM($K17:$O17)/5 -> 142.55734 | U17: =SUM($K17:$O17)/5 -> 142.55734 | V17: =SUM($K17:$O17)/5 -> 142.55734 | W17: =SUM(K17:O17) -> 712.7867 | X17: =SUM(K17:V17) -> 1710.6881 | Y17: =VLOOKUP(J17,[1]BD!$J$2:$W$2575,14,FALSE) -> 3500 | Z17: =Y17-X17 -> 1789.3119 | AA17: =VLOOKUP(J17,Budget!$J$2:$AB$2575,19,FALSE) -> 1458.3333 | AB17: =VLOOKUP(J17,Budget!$J$2:$AB$2575,5,FALSE) -> 291.66667
A18: 1000 | B18: Presidencia Ejecutiva | C18: CEO | D18: CEO | E18: 1001 | F18: Dpto. Direccion Compañia | G18: 6114 | H18: Gastos Generales Oficinas | I18: Expenses | J18: 100010016114 | K18: 310.40374 | L18: 359.26604 | M18: 466.21602 | N18: 57.739282 | O18: 298.40627 | P18: =SUM($K18:$O18)/5 -> 298.40627 | Q18: =SUM($K18:$O18)/5 -> 298.40627 | R18: =SUM($K18:$O18)/5 -> 298.40627 | S18: =SUM($K18:$O18)/5 -> 298.40627 | T18: =SUM($K18:$O18)/5 -> 298.40627 | U18: =SUM($K18:$O18)/5 -> 298.40627 | V18: =SUM($K18:$O18)/5 -> 298.40627 | W18: =SUM(K18:O18) -> 1492.0314 | X18: =SUM(K18:V18) -> 3580.8752 | Y18: =VLOOKUP(J18,[1]BD!$J$2:$W$2575,14,FALSE) -> 5800 | Z18: =Y18-X18 -> 2219.1248 | AA18: =VLOOKUP(J18,Budget!$J$2:$AB$2575,19,FALSE) -> 2416.6667 | AB18: =VLOOKUP(J18,Budget!$J$2:$AB$2575,5,FALSE) -> 483.33333
... A2575: 2861 | B2575: Ste. Accionamiento de Maquinas Eléctricas e Ingeniería | C2575: VPO PLANTAS | D2575: Gerencia Mantención Concentradora | E2575: 5751 | F2575: Dpto. Mantencion Plantas | G2575: 6148 | H2575: Gastos Cafeteria | I2575: Expenses | J2575: 286157516148 | K2575: 66.902745 | L2575: 452.67969 | M2575: 475.0296 | N2575: 278.89789 | O2575: 318.37748 | P2575: =SUM($K2575:$O2575)/5 -> 318.37748 | Q2575: =SUM($K2575:$O2575)/5 -> 318.37748 | R2575: =SUM($K2575:$O2575)/5 -> 318.37748 | S2575: =SUM($K2575:$O2575)/5 -> 318.37748 | T2575: =SUM($K2575:$O2575)/5 -> 318.37748 | U2575: =SUM($K2575:$O2575)/5 -> 318.37748 | V2575: =SUM($K2575:$O2575)/5 -> 318.37748 | W2575: =SUM(K2575:O2575) -> 1591.8874 | X2575: =SUM(K2575:V2575) -> 3820.5298 | Y2575: =VLOOKUP(J2575,[1]BD!$J$2:$W$2575,14,FALSE) -> 6000 | Z2575: =Y2575-X2575 -> 2179.4702 | AA2575: =VLOOKUP(J2575,Budget!$J$2:$AB$2575,19,FALSE) -> 2500 | AB2575: =VLOOKUP(J2575,Budget!$J$2:$AB$2575,5,FALSE) -> 500

Sheet Pivot
A1: VP | B1: (Todas)
A2: Desc Resp | B2: (Todas)
A3: Desc Proc | B3: (Todas)
A5: Etiquetas de fila | B5: Suma de YTD | C5: Suma de Forecast FY | D5: Suma de Budget FY | E5: Suma de BYTD | F5: Suma de Forecast Actual
A6: Contractors | B6: 75359063 | C6: 2.2607719e+08 | D6: #N/A | E6: 1.3241836e+08 | F6: 25221538
A7: Expenses | B7: 68943398 | C7: 2.0683019e+08 | D7: 2.8883223e+08 | E7: 1.1850057e+08 | F7: 24005235
A8: Fuel | B8: 20651154 | C8: 61953461 | D8: 1.2670264e+08 | E8: 51793960 | F8: 11025987
A9: Labor | B9: 65637947 | C9: 1.9691384e+08 | D9: 2.1732266e+08 | E9: 89226602 | F9: 19625147
A10: Maintenance | B10: 14021522 | C10: 42064565 | D10: 58524145 | E10: 24331298 | F10: 4855761
A11: Power | B11: 95169994 | C11: 2.8550998e+08 | D11: 2.9489685e+08 | E11: 1.1144886e+08 | F11: 27124554
A12: Rehandling | B12: 1663778 | C12: 4991333.9 | D12: 2341656 | E12: 2341656 | F12: 0
A13: S&C | B13: 62742817 | C13: 1.8822845e+08 | D13: 2.9604298e+08 | E13: 1.1734875e+08 | F13: 25529832
A14: Spare Parts | B14: 41811184 | C14: 1.2543355e+08 | D14: 1.6463087e+08 | E14: 67497997 | F14: 15504964
A15: Water | B15: 3903450 | C15: 11710350 | D15: 20754245 | E15: 8070627 | F15: 1838413
A16: Total general | B16: 4.4990431e+08 | C16: 1.3497129e+09 | D16: #N/A | E16: 7.2297868e+08 | F16: 1.5473143e+08

Sheet Tabla de Control
B2: Gasto del Mes | C2: Budget abril | G2: Sum gasto ene-abril | H2: Budget Ene-abril | J2: Forecast 4+8 | K2: Budget 2024
B3: Actual | E3: Costos por Naturaleza de Gasto | G3: Year to Date | J3: Full Year
B4: Actual | C4: Forecast | D4: Var | E4: Measure | F4: Units | G4: YTD | H4: BYTD | I4: Var | J4: Forecast FY | K4: Budget 2024 | L4: Var
B5: =Pivot!E6 -> 1.3241836e+08 | C5: =Pivot!F6 -> 25221538 | D5: =B5-C5 -> 1.0719682e+08 | E5: =Pivot!A6 -> Contractors | F5: USD | G5: =Pivot!F6 -> 25221538 | H5: =Pivot!I6 -> 0 | I5: =H5-G5 -> -25221538 | J5: =Pivot!G6 -> 0 | K5: =Pivot!H6 -> 0 | L5: =K5-J5 -> 0
B6: =Pivot!E7 -> 1.1850057e+08 | C6: =Pivot!F7 -> 24005235 | D6: =B6-C6 -> 94495339 | E6: =Pivot!A7 -> Expenses | F6: USD | G6: =Pivot!F7 -> 24005235 | H6: =Pivot!I7 -> 0 | I6: =H6-G6 -> -24005235 | J6: =Pivot!G7 -> 0 | K6: =Pivot!H7 -> 0 | L6: =K6-J6 -> 0
B7: =Pivot!E8 -> 51793960 | C7: =Pivot!F8 -> 11025987 | D7: =B7-C7 -> 40767974 | E7: =Pivot!A8 -> Fuel | F7: USD | G7: =Pivot!F8 -> 11025987 | H7: =Pivot!I8 -> 0 | I7: =H7-G7 -> -11025987 | J7: =Pivot!G8 -> 0 | K7: =Pivot!H8 -> 0 | L7: =K7-J7 -> 0
B8: =Pivot!E9 -> 89226602 | C8: =Pivot!F9 -> 19625147 | D8: =B8-C8 -> 69601455 | E8: =Pivot!A9 -> Labor | F8: USD | G8: =Pivot!F9 -> 19625147 | H8: =Pivot!I9 -> 0 | I8: =H8-G8 -> -19625147 | J8: =Pivot!G9 -> 0 | K8: =Pivot!H9 -> 0 | L8: =K8-J8 -> 0
B9: =Pivot!E10 -> 24331298 | C9: =Pivot!F10 -> 4855761 | D9: =B9-C9 -> 19475537 | E9: =Pivot!A10 -> Maintenance | F9: USD | G9: =Pivot!F10 -> 4855761 | H9: =Pivot!I10 -> 0 | I9: =H9-G9 -> -4855761 | J9: =Pivot!G10 -> 0 | K9: =Pivot!H10 -> 0 | L9: =K9-J9 -> 0
B10: =Pivot!E11 -> 1.1144886e+08 | C10: =Pivot!F11 -> 27124554 | D10: =B10-C10 -> 84324309 | E10: =Pivot!A11 -> Power | F10: USD | G10: =Pivot!F11 -> 27124554 | H10: =Pivot!I11 -> 0 | I10: =H10-G10 -> -27124554 | J10: =Pivot!G11 -> 0 | K10: =Pivot!H11 -> 0 | L10: =K10-J10 -> 0
B11: =Pivot!E12 -> 2341656 | C11: =Pivot!F12 -> 0 | D11: =B11-C11 -> 2341656 | E11: =Pivot!A12 -> Rehandling | F11: USD | G11: =Pivot!F12 -> 0 | H11: =Pivot!I12 -> 0 | I11: =H11-G11 -> 0 | J11: =Pivot!G12 -> 0 | K11: =Pivot!H12 -> 0 | L11: =K11-J11 -> 0
B12: =Pivot!E13 -> 1.1734875e+08 | C12: =Pivot!F13 -> 25529832 | D12: =B12-C12 -> 91818916 | E12: =Pivot!A13 -> S&C | F12: USD | G12: =Pivot!F13 -> 25529832 | H12: =Pivot!I13 -> 0 | I12: =H12-G12 -> -25529832 | J12: =Pivot!G13 -> 0 | K12: =Pivot!H13 -> 0 | L12: =K12-J12 -> 0
B13: =Pivot!E14 -> 67497997 | C13: =Pivot!F14 -> 15504964 | D13: =B13-C13 -> 51993032 | E13: =Pivot!A14 -> Spare Parts | F13: USD | G13: =Pivot!F14 -> 15504964 | H13: =Pivot!I14 -> 0 | I13: =H13-G13 -> -15504964 | J13: =Pivot!G14 -> 0 | K13: =Pivot!H14 -> 0 | L13: =K13-J13 -> 0

Sheet Grafico
B2: Forecast FY | C2: 5.0212379e+08
B3: Contractors | C3: 53729042
B4: Expenses | C4: 1880052.9
B5: Fuel | C5: 61057471
B6: Labor | C6: 16017360
B7: Maintenance | C7: 8349508.2
B8: Power | C8: 4796483.4
B9: Rehandling | C9: -2649677.9
B10: S&C | C10: 38013316
B11: Spare Parts | C11: 23992537
B12: Budget 2024 | C12: -7.0730989e+08

Sheet Hoja2
C2: Naturaleza | D2: Gasto | E2: Gasto en kUSD
C3: Contractors | D3: 1.0562354e+08 | E3: =D3/1000 -> 105623.54
C4: Expenses | D4: 94643892 | E4: =D4/1000 -> 94643.892
C5: S&C | D5: 91943703 | E5: =D5/1000 -> 91943.703
C6: Power | D6: 85767841 | E6: =D6/1000 -> 85767.841
C7: Labor | D7: 72114029 | E7: =D7/1000 -> 72114.029
C8: Spare Parts | D8: 54998966 | E8: =D8/1000 -> 54998.966
C9: Fuel | D9: 40772582 | E9: =D9/1000 -> 40772.582
C10: Maintenance | D10: 19589313 | E10: =D10/1000 -> 19589.313
C11: Water | D11: 6303005.3 | E11: =D11/1000 -> 6303.0053
C12: Rehandling | D12: 2341656 | E12: =D12/1000 -> 2341.656
B27: Naturaleza de Gasto | C27: Suma de Jan-24 | D27: Suma de Feb-24 | E27: Suma de Mar-24 | F27: Suma de Apr-24
B28: Contractors | C28: 20088898 | D28: 16860118 | E28: 18012160 | F28: 20397887
B29: Expenses | C29: 14464211 | D29: 16384376 | E29: 17463959 | F29: 20630852
B30: Fuel | C30: 5544391.7 | D30: 5051102.8 | E30: 4689376.1 | F30: 5366282.9
B31: Labor | C31: 18472835 | D31: 14271283 | E31: 16600359 | F31: 16293470
B32: Maintenance | C32: 3782407.3 | D32: 3503715.7 | E32: 2980494.1 | F32: 3754904.5
B33: Power | C33: 20423111 | D33: 11123181 | E33: 33942073 | F33: 29681629
B34: Rehandling | C34: 1308155.6 | D34: 164451.59 | E34: 191170.75 | F34: 0
B35: S&C | C35: 15903792 | D35: 12551408 | E35: 15754159 | F35: 18533458
B36: Spare Parts | C36: 9793515.6 | D36: 6997088.2 | E36: 12114560 | F36: 12906019
B37: Water | C37: 1322464.4 | D37: 1665752.5 | E37: 695698.48 | F37: 219534.6
B40: Naturaleza de Gasto | C40: Enero | D40: Febrero | E40: Marzo | F40: Abril
B41: Contractors | C41: =C28/1000 -> 20088.898 | D41: =D28/1000 -> 16860.118 | E41: =E28/1000 -> 18012.16 | F41: =F28/1000 -> 20397.887
B42: Expenses | C42: =C29/1000 -> 14464.211 | D42: =D29/1000 -> 16384.376 | E42: =E29/1000 -> 17463.959 | F42: =F29/1000 -> 20630.852
B43: Fuel | C43: =C30/1000 -> 5544.3917 | D43: =D30/1000 -> 5051.1028 | E43: =E30/1000 -> 4689.3761 | F43: =F30/1000 -> 5366.2829
B44: Labor | C44: =C31/1000 -> 18472.835 | D44: =D31/1000 -> 14271.283 | E44: =E31/1000 -> 16600.359 | F44: =F31/1000 -> 16293.47
B45: Maintenance | C45: =C32/1000 -> 3782.4073 | D45: =D32/1000 -> 3503.7157 | E45: =E32/1000 -> 2980.4941 | F45: =F32/1000 -> 3754.9045
B46: Power | C46: =C33/1000 -> 20423.111 | D46: =D33/1000 -> 11123.181 | E46: =E33/1000 -> 33942.073 | F46: =F33/1000 -> 29681.629
B47: Rehandling | C47: =C34/1000 -> 1308.1556 | D47: =D34/1000 -> 164.45159 | E47: =E34/1000 -> 191.17075 | F47: =F34/1000 -> 0
B48: S&C | C48: =C35/1000 -> 15903.792 | D48: =D35/1000 -> 12551.408 | E48: =E35/1000 -> 15754.159 | F48: =F35/1000 -> 18533.458
B49: Spare Parts | C49: =C36/1000 -> 9793.5156 | D49: =D36/1000 -> 6997.0882 | E49: =E36/1000 -> 12114.56 | F49: =F36/1000 -> 12906.019
B50: Water | C50: =C37/1000 -> 1322.4644 | D50: =D37/1000 -> 1665.7525 | E50: =E37/1000 -> 695.69848 | F50: =F37/1000 -> 219.5346
